[
  {
    "Symbol": "AAL.L",
    "Name": "Anglo American PLC"
  },
  {
    "Symbol": "ABDN.L",
    "Name": "Abrdn"
  },
  {
    "Symbol": "ABF.L",
    "Name": "Associated British Foods PLC"
  },
  {
    "Symbol": "ADM.L",
    "Name": "Admiral Group PLC"
  },
  {
    "Symbol": "AHT.L",
    "Name": "Ashtead Group PLC"
  },
  {
    "Symbol": "ANTO.L",
    "Name": "Antofagasta PLC"
  },
  {
    "Symbol": "AV/.L",
    "Name": "Aviva PLC"
  },
  {
    "Symbol": "AZN.L",
    "Name": "AstraZeneca PLC"
  },
  {
    "Symbol": "BA/.L",
    "Name": "BAE Systems PLC"
  },
  {
    "Symbol": "BARC.L",
    "Name": "Barclays PLC"
  },
  {
    "Symbol": "BATS.L",
    "Name": "British American Tobacco PLC"
  },
  {
    "Symbol": "BHP.L",
    "Name": "BHP Group Plc"
  },
  {
    "Symbol": "BKG.L",
    "Name": "Berkeley Group Holdings PLC"
  },
  {
    "Symbol": "BLND.L",
    "Name": "British Land Co"
  },
  {
    "Symbol": "BNZL.L",
    "Name": "Bunzl PLC"
  },
  {
    "Symbol": "BP/.L",
    "Name": "BP PLC"
  },
  {
    "Symbol": "BRBY.L",
    "Name": "Burberry Group"
  },
  {
    "Symbol": "BT/A.L",
    "Name": "BT Group PLC"
  },
  {
    "Symbol": "BTRW.L",
    "Name": "Barratt Redrow PLC"
  },
  {
    "Symbol": "CCH.L",
    "Name": "Coca-Cola HBC AG"
  },
  {
    "Symbol": "CCL.L",
    "Name": "Carnival"
  },
  {
    "Symbol": "CNA.L",
    "Name": "Centrica"
  },
  {
    "Symbol": "CPG.L",
    "Name": "Compass Group PLC"
  },
  {
    "Symbol": "CRDA.L",
    "Name": "Croda International PLC"
  },
  {
    "Symbol": "CRH.L",
    "Name": "CRH"
  },
  {
    "Symbol": "DCC.L",
    "Name": "DCC PLC"
  },
  {
    "Symbol": "DGE.L",
    "Name": "Diageo PLC"
  },
  {
    "Symbol": "DLG.L",
    "Name": "Direct Line Insurance Group"
  },
  {
    "Symbol": "ENT.L",
    "Name": "Entain PLC"
  },
  {
    "Symbol": "EVR.L",
    "Name": "Evraz"
  },
  {
    "Symbol": "EXPN.L",
    "Name": "Experian PLC"
  },
  {
    "Symbol": "EZJ.L",
    "Name": "Easyjet"
  },
  {
    "Symbol": "FERG.L",
    "Name": "Ferguson"
  },
  {
    "Symbol": "FLTR.L",
    "Name": "Flutter Entertainment"
  },
  {
    "Symbol": "FRES.L",
    "Name": "Fresnillo"
  },
  {
    "Symbol": "GLEN.L",
    "Name": "Glencore PLC"
  },
  {
    "Symbol": "GSK.L",
    "Name": "GSK PLC"
  },
  {
    "Symbol": "GVC.L",
    "Name": "GVC Holdings"
  },
  {
    "Symbol": "HL..L",
    "Name": "Hargreaves Lansdown"
  },
  {
    "Symbol": "HLMA.L",
    "Name": "Halma PLC"
  },
  {
    "Symbol": "HSBA.L",
    "Name": "HSBC Holdings PLC"
  },
  {
    "Symbol": "IAG.L",
    "Name": "International Consolidated Airlines Group SA"
  },
  {
    "Symbol": "IDS.L",
    "Name": "Royal Mail"
  },
  {
    "Symbol": "IHG.L",
    "Name": "InterContinental Hotels Group PLC"
  },
  {
    "Symbol": "III.L",
    "Name": "3i Group PLC"
  },
  {
    "Symbol": "IMB.L",
    "Name": "Imperial Brands PLC"
  },
  {
    "Symbol": "INF.L",
    "Name": "Informa PLC"
  },
  {
    "Symbol": "ITRK.L",
    "Name": "Intertek Group PLC"
  },
  {
    "Symbol": "ITV.L",
    "Name": "ITV"
  },
  {
    "Symbol": "JD/.L",
    "Name": "JD Sports Fashion PLC"
  },
  {
    "Symbol": "JE..L",
    "Name": "Just Eat"
  },
  {
    "Symbol": "JMAT.L",
    "Name": "Johnson Matthey"
  },
  {
    "Symbol": "KGF.L",
    "Name": "Kingfisher"
  },
  {
    "Symbol": "LAND.L",
    "Name": "Land Securities Group PLC"
  },
  {
    "Symbol": "LGEN.L",
    "Name": "Legal & General Group PLC"
  },
  {
    "Symbol": "LLOY.L",
    "Name": "Lloyds Banking Group PLC"
  },
  {
    "Symbol": "LSEG.L",
    "Name": "London Stock Exchange Group PLC"
  },
  {
    "Symbol": "MCRO.L",
    "Name": "Micro Focus International"
  },
  {
    "Symbol": "MKS.L",
    "Name": "Marks and Spencer Group"
  },
  {
    "Symbol": "MNDI.L",
    "Name": "Mondi PLC"
  },
  {
    "Symbol": "MNG.L",
    "Name": "M&G PLC"
  },
  {
    "Symbol": "MRO.L",
    "Name": "Melrose Industries"
  },
  {
    "Symbol": "MRW.L",
    "Name": "Morrison (Wm) Supermarkets"
  },
  {
    "Symbol": "NG/.L",
    "Name": "National Grid PLC"
  },
  {
    "Symbol": "NMC.L",
    "Name": "NMC Health"
  },
  {
    "Symbol": "NWG.L",
    "Name": "NatWest Group PLC"
  },
  {
    "Symbol": "NXT.L",
    "Name": "Next PLC"
  },
  {
    "Symbol": "OCDO.L",
    "Name": "Ocado Group"
  },
  {
    "Symbol": "OML.L",
    "Name": "Old Mutual"
  },
  {
    "Symbol": "PRU.L",
    "Name": "Prudential PLC"
  },
  {
    "Symbol": "PSN.L",
    "Name": "Persimmon"
  },
  {
    "Symbol": "PSON.L",
    "Name": "Pearson PLC"
  },
  {
    "Symbol": "REL.L",
    "Name": "RELX PLC"
  },
  {
    "Symbol": "RIO.L",
    "Name": "Rio Tinto PLC"
  },
  {
    "Symbol": "RKT.L",
    "Name": "Reckitt Benckiser Group PLC"
  },
  {
    "Symbol": "RR/.L",
    "Name": "Rolls-Royce Holdings PLC"
  },
  {
    "Symbol": "RRS.L",
    "Name": "Randgold Resources"
  },
  {
    "Symbol": "RS1.L",
    "Name": "RS Group"
  },
  {
    "Symbol": "RSA.L",
    "Name": "RSA Insurance Group"
  },
  {
    "Symbol": "RTO.L",
    "Name": "Rentokil Initial PLC"
  },
  {
    "Symbol": "SBRY.L",
    "Name": "J Sainsbury PLC"
  },
  {
    "Symbol": "SDR.L",
    "Name": "Schroders PLC"
  },
  {
    "Symbol": "SGE.L",
    "Name": "Sage Group PLC/The"
  },
  {
    "Symbol": "SGRO.L",
    "Name": "Segro PLC"
  },
  {
    "Symbol": "SHEL.L",
    "Name": "Shell PLC"
  },
  {
    "Symbol": "SHP.L",
    "Name": "Shire"
  },
  {
    "Symbol": "SKG.L",
    "Name": "Smurfit Kappa Group"
  },
  {
    "Symbol": "SKY.L",
    "Name": "Sky"
  },
  {
    "Symbol": "SMDS.L",
    "Name": "Smith (DS)"
  },
  {
    "Symbol": "SMIN.L",
    "Name": "Smiths Group PLC"
  },
  {
    "Symbol": "SMT.L",
    "Name": "Scottish Mortgage Investment Trust PLC"
  },
  {
    "Symbol": "SN/.L",
    "Name": "Smith & Nephew PLC"
  },
  {
    "Symbol": "SSE.L",
    "Name": "SSE PLC"
  },
  {
    "Symbol": "STAN.L",
    "Name": "Standard Chartered PLC"
  },
  {
    "Symbol": "STJ.L",
    "Name": "St. James's Place"
  },
  {
    "Symbol": "SVT.L",
    "Name": "Severn Trent PLC"
  },
  {
    "Symbol": "TSCO.L",
    "Name": "Tesco PLC"
  },
  {
    "Symbol": "TUI.L",
    "Name": "TUI AG"
  },
  {
    "Symbol": "TW..L",
    "Name": "Taylor Wimpey"
  },
  {
    "Symbol": "ULVR.L",
    "Name": "Unilever PLC"
  },
  {
    "Symbol": "UU/.L",
    "Name": "United Utilities Group PLC"
  },
  {
    "Symbol": "VOD.L",
    "Name": "Vodafone Group PLC"
  },
  {
    "Symbol": "WPP.L",
    "Name": "WPP"
  },
  {
    "Symbol": "WTB.L",
    "Name": "Whitbread PLC"
  }
]